{
    "relationships": [
        {
            "name": "Fabi\u00e1n Mazzei",
            "href": "https://www.whosdatedwho.com/dating/fabian-mazzei",
            "relationship_type": 4,
            "start_date": "24th Dec 2007",
            "end_date": "present",
            "length": "16 years",
            "start_months_since_1900": 1295,
            "end_months_since_1900": -1,
            "length_in_months": 192
        },
        {
            "name": "Adri\u00e1n Suar",
            "href": "https://www.whosdatedwho.com/dating/adrian-suar",
            "relationship_type": 4,
            "start_date": "1992",
            "end_date": "Mar 2004",
            "length": "12 years",
            "start_months_since_1900": 1104,
            "end_months_since_1900": 1250,
            "length_in_months": 144
        },
        {
            "name": "Ruben Torrente",
            "href": "https://www.whosdatedwho.com/dating/ruben-torrente",
            "relationship_type": 4,
            "start_date": "1987",
            "end_date": "1991",
            "length": "4 years",
            "start_months_since_1900": 1044,
            "end_months_since_1900": 1092,
            "length_in_months": 48
        }
    ],
    "details": {
        "First Name": "Araceli",
        "Middle Name": "Edith",
        "Last Name": "Mazzei",
        "Maiden Name": "Gonz\u00e1lez",
        "Full Name at Birth": "Araceli Edith Gonz\u00e1lez",
        "Alternative Name": "Ara",
        "Birthday": "1967",
        "Birthplace": "BA",
        "Height": "171",
        "Weight": "NA",
        "Zodiac Sign": "4",
        "Sexuality": "Straight",
        "Religion": "1",
        "Ethnicity": "6",
        "Nationality": "28",
        "Occupation": "8"
    }
}