{
    "relationships": [
        {
            "name": "Christopher Connelly",
            "href": "https://www.whosdatedwho.com/dating/christopher-connelly",
            "relationship_type": 4,
            "start_date": "Dec 1968",
            "end_date": "7th Dec 1988",
            "length": "20 years",
            "start_months_since_1900": 827,
            "end_months_since_1900": 1067,
            "length_in_months": 240
        }
    ],
    "details": {
        "First Name": "Cindy",
        "Middle Name": "Annette",
        "Last Name": "Carol",
        "Maiden Name": "Sydes",
        "Full Name at Birth": "Carol Annette Sydes",
        "Alternative Name": "NA",
        "Birthday": "1944",
        "Birthplace": "California",
        "Height": "NA",
        "Weight": "NA",
        "Zodiac Sign": "10",
        "Sexuality": "Straight",
        "Religion": "1",
        "Ethnicity": "6",
        "Nationality": "91",
        "Occupation": "8"
    }
}