{
    "relationships": [
        {
            "name": "Michael Sterling (Executive Director)",
            "href": "https://www.whosdatedwho.com/dating/michael-sterling-executive-director",
            "relationship_type": 4,
            "start_date": "Jan 2016",
            "end_date": "Mar 2023",
            "length": "7 years",
            "start_months_since_1900": 1392,
            "end_months_since_1900": 1478,
            "length_in_months": 84
        },
        {
            "name": "Kevin McCall",
            "href": "https://www.whosdatedwho.com/dating/kevin-mccall",
            "relationship_type": 2,
            "start_date": "Jan 2013",
            "end_date": "Jan 2015",
            "length": "2 years",
            "start_months_since_1900": 1356,
            "end_months_since_1900": 1380,
            "length_in_months": 24
        },
        {
            "name": "Flo Rida",
            "href": "https://www.whosdatedwho.com/dating/flo-rida",
            "relationship_type": 2,
            "start_date": "Jun 2010",
            "end_date": "Mar 2011",
            "length": "9 months",
            "start_months_since_1900": 1325,
            "end_months_since_1900": 1334,
            "length_in_months": 9
        },
        {
            "name": "Jamie Foxx",
            "href": "https://www.whosdatedwho.com/dating/jamie-foxx",
            "relationship_type": 2,
            "start_date": "Mar 2006",
            "end_date": "Jun 2006",
            "length": "3 months",
            "start_months_since_1900": 1274,
            "end_months_since_1900": 1277,
            "length_in_months": 3
        },
        {
            "name": "Kerry Rhodes",
            "href": "https://www.whosdatedwho.com/dating/kerry-rhodes",
            "relationship_type": 2,
            "start_date": "Dec 2005",
            "end_date": "Mar 2006",
            "length": "3 months",
            "start_months_since_1900": 1271,
            "end_months_since_1900": 1274,
            "length_in_months": 3
        },
        {
            "name": "Henry Simmons",
            "href": "https://www.whosdatedwho.com/dating/henry-simmons",
            "relationship_type": 2,
            "start_date": "Jun 2005",
            "end_date": "Nov 2005",
            "length": "5 months",
            "start_months_since_1900": 1265,
            "end_months_since_1900": 1270,
            "length_in_months": 5
        },
        {
            "name": "Nick Cannon",
            "href": "https://www.whosdatedwho.com/dating/nick-cannon",
            "relationship_type": 3,
            "start_date": "Apr 2005",
            "end_date": "Jun 2005",
            "length": "2 months",
            "start_months_since_1900": 1263,
            "end_months_since_1900": 1265,
            "length_in_months": 2
        },
        {
            "name": "Hosea Chanchez",
            "href": "https://www.whosdatedwho.com/dating/hosea-chanchez",
            "relationship_type": 2,
            "start_date": "May 2002",
            "end_date": "Mar 2005",
            "length": "2 years",
            "start_months_since_1900": 1228,
            "end_months_since_1900": 1262,
            "length_in_months": 24
        },
        {
            "name": "Lance Gross",
            "href": "https://www.whosdatedwho.com/dating/lance-gross",
            "relationship_type": 2,
            "start_date": "Jan 1999",
            "end_date": "Mar 2010",
            "length": "11 years",
            "start_months_since_1900": 1188,
            "end_months_since_1900": 1322,
            "length_in_months": 132
        }
    ],
    "details": {
        "First Name": "Eva",
        "Middle Name": "Marcille",
        "Last Name": "Marcille",
        "Maiden Name": "Pigford",
        "Full Name at Birth": "Eva Marcille Pigford",
        "Alternative Name": "Eva Marcille, Miss Eva, Eva the Diva, Eva Marcille Pigford, Eva Diva",
        "Birthday": "1984",
        "Birthplace": "USA",
        "Height": "170",
        "Weight": "139lbs (63 kg)",
        "Zodiac Sign": "5",
        "Sexuality": "Straight",
        "Religion": "36",
        "Ethnicity": "8",
        "Nationality": "91",
        "Occupation": "8"
    }
}