{
    "relationships": [
        {
            "name": "Scarlett Sabet",
            "href": "https://www.whosdatedwho.com/dating/scarlett-sabet",
            "relationship_type": 2,
            "start_date": "2015",
            "end_date": "2015",
            "length": "-",
            "start_months_since_1900": 1380,
            "end_months_since_1900": 1380,
            "length_in_months": -1
        },
        {
            "name": "Aveyanda Skye",
            "href": "https://www.whosdatedwho.com/dating/aveyanda-skye",
            "relationship_type": 2,
            "start_date": "2013",
            "end_date": "2015",
            "length": "2 years",
            "start_months_since_1900": 1356,
            "end_months_since_1900": 1380,
            "length_in_months": 24
        },
        {
            "name": "Jimena Gomez-Paratcha",
            "href": "https://www.whosdatedwho.com/dating/jimena-gomez-paratcha",
            "relationship_type": 4,
            "start_date": "1994",
            "end_date": "2006",
            "length": "12 years",
            "start_months_since_1900": 1128,
            "end_months_since_1900": 1272,
            "length_in_months": 144
        },
        {
            "name": "Sandra Taylor",
            "href": "https://www.whosdatedwho.com/dating/sandra-taylor",
            "relationship_type": 3,
            "start_date": "1994",
            "end_date": "1994",
            "length": "-",
            "start_months_since_1900": 1128,
            "end_months_since_1900": 1128,
            "length_in_months": -1
        },
        {
            "name": "Patricia Ecker",
            "href": "https://www.whosdatedwho.com/dating/patricia-ecker",
            "relationship_type": 4,
            "start_date": "1985",
            "end_date": "Jan 1995",
            "length": "10 years",
            "start_months_since_1900": 1020,
            "end_months_since_1900": 1140,
            "length_in_months": 120
        },
        {
            "name": "Lori Mattox",
            "href": "https://www.whosdatedwho.com/dating/lori-mattox",
            "relationship_type": 2,
            "start_date": "Aug 1975",
            "end_date": "Mar 1976",
            "length": "7 months",
            "start_months_since_1900": 907,
            "end_months_since_1900": 914,
            "length_in_months": 7
        },
        {
            "name": "Fabienne Fabre",
            "href": "https://www.whosdatedwho.com/dating/fabienne-shine",
            "relationship_type": 3,
            "start_date": "1975",
            "end_date": "1975",
            "length": "-",
            "start_months_since_1900": 900,
            "end_months_since_1900": 900,
            "length_in_months": -1
        },
        {
            "name": "Sabel Starr",
            "href": "https://www.whosdatedwho.com/dating/sabel-starr",
            "relationship_type": 2,
            "start_date": "1975",
            "end_date": "1976",
            "length": "1 year",
            "start_months_since_1900": 900,
            "end_months_since_1900": 912,
            "length_in_months": 12
        },
        {
            "name": "Krissy Wood",
            "href": "https://www.whosdatedwho.com/dating/krissy-wood",
            "relationship_type": 2,
            "start_date": "1974",
            "end_date": "1974",
            "length": "-",
            "start_months_since_1900": 888,
            "end_months_since_1900": 888,
            "length_in_months": -1
        },
        {
            "name": "Bebe Buell",
            "href": "https://www.whosdatedwho.com/dating/bebe-buell",
            "relationship_type": 3,
            "start_date": "1974",
            "end_date": "1974",
            "length": "-",
            "start_months_since_1900": 888,
            "end_months_since_1900": 888,
            "length_in_months": -1
        },
        {
            "name": "Queenie",
            "href": "https://www.whosdatedwho.com/dating/queenie",
            "relationship_type": 3,
            "start_date": "1972",
            "end_date": "1972",
            "length": "-",
            "start_months_since_1900": 864,
            "end_months_since_1900": 864,
            "length_in_months": -1
        },
        {
            "name": "Connie Hamzy",
            "href": "https://www.whosdatedwho.com/dating/connie-hamzy",
            "relationship_type": 3,
            "start_date": "Aug 1971",
            "end_date": "Aug 1971",
            "length": "-",
            "start_months_since_1900": 859,
            "end_months_since_1900": 859,
            "length_in_months": -1
        },
        {
            "name": "Kanuko",
            "href": "https://www.whosdatedwho.com/dating/kanuko",
            "relationship_type": 3,
            "start_date": "1971",
            "end_date": "1971",
            "length": "-",
            "start_months_since_1900": 852,
            "end_months_since_1900": 852,
            "length_in_months": -1
        },
        {
            "name": "Charlotte Martin",
            "href": "https://www.whosdatedwho.com/dating/charlotte-martin",
            "relationship_type": 2,
            "start_date": "Jan 1970",
            "end_date": "Oct 1983",
            "length": "13 years",
            "start_months_since_1900": 840,
            "end_months_since_1900": 1005,
            "length_in_months": 156
        },
        {
            "name": "Catherine James",
            "href": "https://www.whosdatedwho.com/dating/catherine-james",
            "relationship_type": 2,
            "start_date": "Jan 1969",
            "end_date": "Jan 1969",
            "length": "-",
            "start_months_since_1900": 828,
            "end_months_since_1900": 828,
            "length_in_months": -1
        },
        {
            "name": "Pamela Des Barres",
            "href": "https://www.whosdatedwho.com/dating/pamela-des-barres",
            "relationship_type": 3,
            "start_date": "1969",
            "end_date": "Apr 1972",
            "length": "3 years",
            "start_months_since_1900": 828,
            "end_months_since_1900": 867,
            "length_in_months": 36
        },
        {
            "name": "Cindy Wells",
            "href": "https://www.whosdatedwho.com/dating/cindy-wells",
            "relationship_type": 3,
            "start_date": "1969",
            "end_date": "1969",
            "length": "-",
            "start_months_since_1900": 828,
            "end_months_since_1900": 828,
            "length_in_months": -1
        },
        {
            "name": "Josette Caruso",
            "href": "https://www.whosdatedwho.com/dating/josette-caruso",
            "relationship_type": 3,
            "start_date": "1969",
            "end_date": "1969",
            "length": "-",
            "start_months_since_1900": 828,
            "end_months_since_1900": 828,
            "length_in_months": -1
        },
        {
            "name": "Lynn Collins",
            "href": "https://www.whosdatedwho.com/dating/lynn-collins-socialite",
            "relationship_type": 3,
            "start_date": "1968",
            "end_date": "1969",
            "length": "1 year",
            "start_months_since_1900": 816,
            "end_months_since_1900": 828,
            "length_in_months": 12
        },
        {
            "name": "Heather Daltrey",
            "href": "https://www.whosdatedwho.com/dating/heather-daltrey",
            "relationship_type": 2,
            "start_date": "1967",
            "end_date": "1967",
            "length": "-",
            "start_months_since_1900": 804,
            "end_months_since_1900": 804,
            "length_in_months": -1
        },
        {
            "name": "Cassandra Peterson",
            "href": "https://www.whosdatedwho.com/dating/cassandra-peterson",
            "relationship_type": 3,
            "start_date": "1967",
            "end_date": "1967",
            "length": "-",
            "start_months_since_1900": 804,
            "end_months_since_1900": 804,
            "length_in_months": -1
        },
        {
            "name": "Dana Gillespie",
            "href": "https://www.whosdatedwho.com/dating/dana-gillespie",
            "relationship_type": 3,
            "start_date": "1966",
            "end_date": "1966",
            "length": "-",
            "start_months_since_1900": 792,
            "end_months_since_1900": 792,
            "length_in_months": -1
        },
        {
            "name": "Jackie DeShannon",
            "href": "https://www.whosdatedwho.com/dating/jackie-deshannon",
            "relationship_type": 2,
            "start_date": "1964",
            "end_date": "1965",
            "length": "1 year",
            "start_months_since_1900": 768,
            "end_months_since_1900": 780,
            "length_in_months": 12
        },
        {
            "name": "Alycen Rowse",
            "href": "https://www.whosdatedwho.com/dating/alycen-rowse",
            "relationship_type": 1,
            "start_date": "",
            "end_date": "",
            "length": "-",
            "start_months_since_1900": -1,
            "end_months_since_1900": -1,
            "length_in_months": -1
        },
        {
            "name": "Linda McCartney",
            "href": "https://www.whosdatedwho.com/dating/linda-mccartney",
            "relationship_type": 1,
            "start_date": "",
            "end_date": "",
            "length": "-",
            "start_months_since_1900": -1,
            "end_months_since_1900": -1,
            "length_in_months": -1
        },
        {
            "name": "Christine Boris",
            "href": "https://www.whosdatedwho.com/dating/christine-boris",
            "relationship_type": 3,
            "start_date": "",
            "end_date": "",
            "length": "-",
            "start_months_since_1900": -1,
            "end_months_since_1900": -1,
            "length_in_months": -1
        },
        {
            "name": "Corel Shields",
            "href": "https://www.whosdatedwho.com/dating/corel-shields",
            "relationship_type": 3,
            "start_date": "",
            "end_date": "",
            "length": "-",
            "start_months_since_1900": -1,
            "end_months_since_1900": -1,
            "length_in_months": -1
        }
    ],
    "details": {
        "First Name": "Jimmy",
        "Middle Name": "Patrick",
        "Last Name": "Page",
        "Maiden Name": "NA",
        "Full Name at Birth": "James Patrick Page",
        "Alternative Name": "S. Flavius Mercurius, Jimmy Page, Jimmy, Pagey, Charles Obscure",
        "Birthday": "1944",
        "Birthplace": "UK",
        "Height": "183",
        "Weight": "185lbs (84 kg)",
        "Zodiac Sign": "13",
        "Sexuality": "Straight",
        "Religion": "10",
        "Ethnicity": "6",
        "Nationality": "8",
        "Occupation": "1"
    }
}