{
    "relationships": [
        {
            "name": "Alexander Borromeo",
            "href": "https://www.whosdatedwho.com/dating/alexander-borromeo",
            "relationship_type": 2,
            "start_date": "2017",
            "end_date": "2018",
            "length": "1 year",
            "start_months_since_1900": 1404,
            "end_months_since_1900": 1416,
            "length_in_months": 12
        },
        {
            "name": "Paulo Avelino",
            "href": "https://www.whosdatedwho.com/dating/paulo-avelino",
            "relationship_type": 2,
            "start_date": "2014",
            "end_date": "2015",
            "length": "1 year",
            "start_months_since_1900": 1368,
            "end_months_since_1900": 1380,
            "length_in_months": 12
        },
        {
            "name": "Chandler Parsons",
            "href": "https://www.whosdatedwho.com/dating/chandler-parsons",
            "relationship_type": 3,
            "start_date": "Oct 2013",
            "end_date": "Oct 2013",
            "length": "-",
            "start_months_since_1900": 1365,
            "end_months_since_1900": 1365,
            "length_in_months": -1
        },
        {
            "name": "Apl.de.Ap",
            "href": "https://www.whosdatedwho.com/dating/apl-de-ap",
            "relationship_type": 3,
            "start_date": "Mar 2013",
            "end_date": "Apr 2013",
            "length": "1 month",
            "start_months_since_1900": 1358,
            "end_months_since_1900": 1359,
            "length_in_months": 1
        },
        {
            "name": "Pierre-Emmanuel Plassart",
            "href": "https://www.whosdatedwho.com/dating/pierre-emmanuel-plassart",
            "relationship_type": 2,
            "start_date": "Sep 2012",
            "end_date": "Feb 2013",
            "length": "5 months",
            "start_months_since_1900": 1352,
            "end_months_since_1900": 1357,
            "length_in_months": 5
        },
        {
            "name": "Piolo Pascual",
            "href": "https://www.whosdatedwho.com/dating/piolo-pascual",
            "relationship_type": 2,
            "start_date": "Oct 2010",
            "end_date": "2011",
            "length": "3 months",
            "start_months_since_1900": 1329,
            "end_months_since_1900": 1332,
            "length_in_months": 3
        },
        {
            "name": "Lino S. Cayetano",
            "href": "https://www.whosdatedwho.com/dating/lino-s-cayetano",
            "relationship_type": 2,
            "start_date": "2007",
            "end_date": "2007",
            "length": "-",
            "start_months_since_1900": 1284,
            "end_months_since_1900": 1284,
            "length_in_months": -1
        },
        {
            "name": "Billy Crawford",
            "href": "https://www.whosdatedwho.com/dating/billy-crawford",
            "relationship_type": 3,
            "start_date": "2005",
            "end_date": "2007",
            "length": "2 years",
            "start_months_since_1900": 1260,
            "end_months_since_1900": 1284,
            "length_in_months": 24
        },
        {
            "name": "Rico Blanco",
            "href": "https://www.whosdatedwho.com/dating/rico-blanco",
            "relationship_type": 2,
            "start_date": "2003",
            "end_date": "2005",
            "length": "2 years",
            "start_months_since_1900": 1236,
            "end_months_since_1900": 1260,
            "length_in_months": 24
        },
        {
            "name": "Ugo de Charette",
            "href": "https://www.whosdatedwho.com/dating/ugo-de-charette",
            "relationship_type": 2,
            "start_date": "",
            "end_date": "",
            "length": "-",
            "start_months_since_1900": -1,
            "end_months_since_1900": -1,
            "length_in_months": -1
        }
    ],
    "details": {
        "First Name": "Maria Kristina Cassandra",
        "Middle Name": "Cuneta",
        "Last Name": "Concepcion",
        "Maiden Name": "NA",
        "Full Name at Birth": "Maria Kristina Cassandra Cuneta Concepcion",
        "Alternative Name": "Kace, Kooki, Sandy, Cassandra, Kristina, KC Concepcion, Kooks, Tina, Kc",
        "Birthday": "1985",
        "Birthplace": "Philippines",
        "Height": "165",
        "Weight": "117lbs (53 kg)",
        "Zodiac Sign": "7",
        "Sexuality": "Straight",
        "Religion": "13",
        "Ethnicity": "8",
        "Nationality": "16",
        "Occupation": "8"
    }
}