{
    "relationships": [
        {
            "name": "Bess Meredyth",
            "href": "https://www.whosdatedwho.com/dating/bess-meredyth",
            "relationship_type": 4,
            "start_date": "1928",
            "end_date": "Apr 1961",
            "length": "33 years",
            "start_months_since_1900": 336,
            "end_months_since_1900": 735,
            "length_in_months": 396
        },
        {
            "name": "Lili Damita",
            "href": "https://www.whosdatedwho.com/dating/lili-damita",
            "relationship_type": 4,
            "start_date": "1924",
            "end_date": "1926",
            "length": "2 years",
            "start_months_since_1900": 288,
            "end_months_since_1900": 312,
            "length_in_months": 24
        },
        {
            "name": "Lucy Doraine",
            "href": "https://www.whosdatedwho.com/dating/lucy-doraine",
            "relationship_type": 4,
            "start_date": "1917",
            "end_date": "1923",
            "length": "6 years",
            "start_months_since_1900": 204,
            "end_months_since_1900": 276,
            "length_in_months": 72
        },
        {
            "name": "Louise Fazenda",
            "href": "https://www.whosdatedwho.com/dating/louise-fazenda",
            "relationship_type": 3,
            "start_date": "",
            "end_date": "",
            "length": "-",
            "start_months_since_1900": -1,
            "end_months_since_1900": -1,
            "length_in_months": -1
        },
        {
            "name": "Mae Madison",
            "href": "https://www.whosdatedwho.com/dating/mae-madison",
            "relationship_type": 2,
            "start_date": "",
            "end_date": "",
            "length": "-",
            "start_months_since_1900": -1,
            "end_months_since_1900": -1,
            "length_in_months": -1
        },
        {
            "name": "Bella Darvi",
            "href": "https://www.whosdatedwho.com/dating/bella-darvi",
            "relationship_type": 3,
            "start_date": "",
            "end_date": "",
            "length": "-",
            "start_months_since_1900": -1,
            "end_months_since_1900": -1,
            "length_in_months": -1
        }
    ],
    "details": {
        "First Name": "Michael",
        "Middle Name": "NA",
        "Last Name": "Curtiz",
        "Maiden Name": "NA",
        "Full Name at Birth": "Man\u00f3 Kert\u00e9sz Kaminer",
        "Alternative Name": "Man\u00f3 Kert\u00e9sz Kaminer, Michael Curtiz",
        "Birthday": "1886",
        "Birthplace": "Austria-Hungary (now Hungary)",
        "Height": "175",
        "Weight": "NA",
        "Zodiac Sign": "13",
        "Sexuality": "Straight",
        "Religion": "31",
        "Ethnicity": "6",
        "Nationality": "31",
        "Occupation": "9"
    }
}