{
    "relationships": [
        {
            "name": "21 Savage",
            "href": "https://www.whosdatedwho.com/dating/21-savage",
            "relationship_type": 2,
            "start_date": "May 2020",
            "end_date": "May 2020",
            "length": "-",
            "start_months_since_1900": 1444,
            "end_months_since_1900": 1444,
            "length_in_months": -1
        },
        {
            "name": "Key Glock",
            "href": "https://www.whosdatedwho.com/dating/key-glock",
            "relationship_type": 2,
            "start_date": "Feb 2019",
            "end_date": "Jun 2020",
            "length": "1 year",
            "start_months_since_1900": 1429,
            "end_months_since_1900": 1445,
            "length_in_months": 12
        },
        {
            "name": "Bandit Gang Marco",
            "href": "https://www.whosdatedwho.com/dating/bandit-gang-marco-93340622",
            "relationship_type": 2,
            "start_date": "",
            "end_date": "",
            "length": "-",
            "start_months_since_1900": -1,
            "end_months_since_1900": -1,
            "length_in_months": -1
        }
    ],
    "details": {
        "First Name": "Alyssa",
        "Middle Name": "Michelle",
        "Last Name": "Stephens",
        "Maiden Name": "NA",
        "Full Name at Birth": "Alyssa Michelle Stephens",
        "Alternative Name": "Miss Mulatto, Mulatto, Big Latto, Mula, Latto, Alyssa Michelle Stephens",
        "Birthday": "1998",
        "Birthplace": "USA",
        "Height": "168",
        "Weight": "144lbs (65 kg)",
        "Zodiac Sign": "13",
        "Sexuality": "Straight",
        "Religion": "1",
        "Ethnicity": "8",
        "Nationality": "91",
        "Occupation": "1"
    }
}