{
    "relationships": [
        {
            "name": "Leyla Milani",
            "href": "https://www.whosdatedwho.com/dating/leyla-milani",
            "relationship_type": 2,
            "start_date": "Jul 2007",
            "end_date": "Sep 2007",
            "length": "2 months",
            "start_months_since_1900": 1290,
            "end_months_since_1900": 1292,
            "length_in_months": 2
        },
        {
            "name": "Essence Atkins",
            "href": "https://www.whosdatedwho.com/dating/essence-atkins",
            "relationship_type": 2,
            "start_date": "Dec 2001",
            "end_date": "Nov 2003",
            "length": "1 year",
            "start_months_since_1900": 1223,
            "end_months_since_1900": 1246,
            "length_in_months": 12
        },
        {
            "name": "Erica Vittina Phillips",
            "href": "https://www.whosdatedwho.com/dating/erica-vittina-phillips",
            "relationship_type": 2,
            "start_date": "Jul 2001",
            "end_date": "Nov 2001",
            "length": "4 months",
            "start_months_since_1900": 1218,
            "end_months_since_1900": 1222,
            "length_in_months": 4
        }
    ],
    "details": {
        "First Name": "Ron",
        "Middle Name": "NA",
        "Last Name": "Truppa",
        "Maiden Name": "NA",
        "Full Name at Birth": "NA",
        "Alternative Name": "Ron T, Truppa, Ronnie T, Ronnie",
        "Birthday": "8th May",
        "Birthplace": "Rhode Island",
        "Height": "174",
        "Weight": "170lbs (77 kg)",
        "Zodiac Sign": "3",
        "Sexuality": "Straight",
        "Religion": "13",
        "Ethnicity": "6",
        "Nationality": "91",
        "Occupation": "9"
    }
}