{
    "relationships": [
        {
            "name": "Corinne Kingsbury",
            "href": "https://www.whosdatedwho.com/dating/corinne-kingsbury",
            "relationship_type": 4,
            "start_date": "Nov 2003",
            "end_date": "Aug 2008",
            "length": "4 years",
            "start_months_since_1900": 1246,
            "end_months_since_1900": 1303,
            "length_in_months": 48
        },
        {
            "name": "Lauren Graham",
            "href": "https://www.whosdatedwho.com/dating/lauren-graham",
            "relationship_type": 2,
            "start_date": "2002",
            "end_date": "2002",
            "length": "-",
            "start_months_since_1900": 1224,
            "end_months_since_1900": 1224,
            "length_in_months": -1
        },
        {
            "name": "Whitney Allen",
            "href": "https://www.whosdatedwho.com/dating/whitney-allen",
            "relationship_type": 2,
            "start_date": "2001",
            "end_date": "2001",
            "length": "-",
            "start_months_since_1900": 1212,
            "end_months_since_1900": 1212,
            "length_in_months": -1
        },
        {
            "name": "Plum Sykes",
            "href": "https://www.whosdatedwho.com/dating/plum-sykes",
            "relationship_type": 2,
            "start_date": "2000",
            "end_date": "2000",
            "length": "-",
            "start_months_since_1900": 1200,
            "end_months_since_1900": 1200,
            "length_in_months": -1
        },
        {
            "name": "Jennifer Aniston",
            "href": "https://www.whosdatedwho.com/dating/jennifer-aniston",
            "relationship_type": 2,
            "start_date": "Nov 1995",
            "end_date": "Feb 1998",
            "length": "2 years",
            "start_months_since_1900": 1150,
            "end_months_since_1900": 1177,
            "length_in_months": 24
        },
        {
            "name": "Sandra Bullock",
            "href": "https://www.whosdatedwho.com/dating/sandra-bullock",
            "relationship_type": 2,
            "start_date": "Oct 1990",
            "end_date": "Oct 1995",
            "length": "5 years",
            "start_months_since_1900": 1089,
            "end_months_since_1900": 1149,
            "length_in_months": 60
        }
    ],
    "details": {
        "First Name": "Tate",
        "Middle Name": "Buckley",
        "Last Name": "Donovan",
        "Maiden Name": "NA",
        "Full Name at Birth": "Tate Buckley Donovan",
        "Alternative Name": "NA",
        "Birthday": "1963",
        "Birthplace": "NJ",
        "Height": "183",
        "Weight": "NA",
        "Zodiac Sign": "10",
        "Sexuality": "Straight",
        "Religion": "13",
        "Ethnicity": "6",
        "Nationality": "91",
        "Occupation": "8"
    }
}