{
    "relationships": [
        {
            "name": "Hayden Kho",
            "href": "https://www.whosdatedwho.com/dating/hayden-kho",
            "relationship_type": 4,
            "start_date": "2005",
            "end_date": "present",
            "length": "19 years",
            "start_months_since_1900": 1260,
            "end_months_since_1900": -1,
            "length_in_months": 228
        },
        {
            "name": "Atom Henares",
            "href": "https://www.whosdatedwho.com/dating/atom-henares",
            "relationship_type": 4,
            "start_date": "",
            "end_date": "",
            "length": "-",
            "start_months_since_1900": -1,
            "end_months_since_1900": -1,
            "length_in_months": -1
        }
    ],
    "details": {
        "First Name": "Maria Victoria",
        "Middle Name": "Gonzalez",
        "Last Name": "Kho",
        "Maiden Name": "Belo",
        "Full Name at Birth": "Maria Victoria Gonzalez Belo-Kho",
        "Alternative Name": "Dra. Belo",
        "Birthday": "1956",
        "Birthplace": "Philippines",
        "Height": "NA",
        "Weight": "NA",
        "Zodiac Sign": "9",
        "Sexuality": "Straight",
        "Religion": "13",
        "Ethnicity": "3",
        "Nationality": "16",
        "Occupation": "6"
    }
}